{
  "total_time": 20797.132769584656,
  "total_models": 12,
  "successful": 12,
  "failed": 0,
  "success_rate": 100.0,
  "results": [
    {
      "config": "7n_1n",
      "model_type": "xgboost",
      "success": true,
      "training_time": 67.94943356513977,
      "timestamp": "2025-10-03T23:05:06.349944",
      "test_rmse": 0.284122557614786,
      "test_r2": 0.759841891887616,
      "best_params": {
        "learning_rate": 0.1,
        "max_depth": 3,
        "n_estimators": 500,
        "subsample": 1.0
      }
    },
    {
      "config": "7n_1n",
      "model_type": "lstm",
      "success": true,
      "training_time": 443.4944443702698,
      "timestamp": "2025-10-03T23:12:30.353569",
      "test_rmse": 0.5450556204668436,
      "test_r2": 0.11617258735286895,
      "best_params": {
        "batch_size": 32,
        "dropout": 0.2,
        "n_layers": 2,
        "units": 32
      }
    },
    {
      "config": "30n_1n",
      "model_type": "xgboost",
      "success": true,
      "training_time": 274.63967728614807,
      "timestamp": "2025-10-03T23:17:05.505122",
      "test_rmse": 0.21260567227425592,
      "test_r2": 0.8656148451451403,
      "best_params": {
        "learning_rate": 0.01,
        "max_depth": 7,
        "n_estimators": 500,
        "subsample": 0.5
      }
    },
    {
      "config": "30n_1n",
      "model_type": "lstm",
      "success": true,
      "training_time": 2025.171108007431,
      "timestamp": "2025-10-03T23:50:51.176945",
      "test_rmse": 0.5900982107759413,
      "test_r2": -0.03526181898764347,
      "best_params": {
        "batch_size": 32,
        "dropout": 0.2,
        "n_layers": 1,
        "units": 64
      }
    },
    {
      "config": "30n_7n",
      "model_type": "xgboost",
      "success": true,
      "training_time": 267.5455815792084,
      "timestamp": "2025-10-03T23:55:19.228928",
      "test_rmse": 0.2534688798685862,
      "test_r2": 0.8090107926098805,
      "best_params": {
        "learning_rate": 0.1,
        "max_depth": 5,
        "n_estimators": 500,
        "subsample": 1.0
      }
    },
    {
      "config": "30n_7n",
      "model_type": "lstm",
      "success": true,
      "training_time": 2065.9767429828644,
      "timestamp": "2025-10-04T00:29:45.706335",
      "test_rmse": 0.5110243213832539,
      "test_r2": 0.22367660241404186,
      "best_params": {
        "batch_size": 32,
        "dropout": 0.2,
        "n_layers": 2,
        "units": 64
      }
    },
    {
      "config": "30n_30n",
      "model_type": "xgboost",
      "success": true,
      "training_time": 277.2646059989929,
      "timestamp": "2025-10-04T00:34:23.475023",
      "test_rmse": 0.36922566087237974,
      "test_r2": 0.5938733429409442,
      "best_params": {
        "learning_rate": 0.1,
        "max_depth": 5,
        "n_estimators": 500,
        "subsample": 0.5
      }
    },
    {
      "config": "30n_30n",
      "model_type": "lstm",
      "success": true,
      "training_time": 2191.712866783142,
      "timestamp": "2025-10-04T01:10:55.688405",
      "test_rmse": 0.5541300624478136,
      "test_r2": 0.08525263469763356,
      "best_params": {
        "batch_size": 32,
        "dropout": 0.5,
        "n_layers": 1,
        "units": 64
      }
    },
    {
      "config": "90n_7n",
      "model_type": "xgboost",
      "success": true,
      "training_time": 788.0537419319153,
      "timestamp": "2025-10-04T01:24:04.245328",
      "test_rmse": 0.22913136731472086,
      "test_r2": 0.839984757884968,
      "best_params": {
        "learning_rate": 0.01,
        "max_depth": 5,
        "n_estimators": 300,
        "subsample": 0.8
      }
    },
    {
      "config": "90n_7n",
      "model_type": "lstm",
      "success": true,
      "training_time": 5318.591502904892,
      "timestamp": "2025-10-04T02:52:43.337534",
      "test_rmse": 0.3510538582934928,
      "test_r2": 0.6243877387550735,
      "best_params": {
        "batch_size": 32,
        "dropout": 0.2,
        "n_layers": 1,
        "units": 64
      }
    },
    {
      "config": "90n_30n",
      "model_type": "xgboost",
      "success": true,
      "training_time": 822.2265746593475,
      "timestamp": "2025-10-04T03:06:26.067072",
      "test_rmse": 0.3073387095694993,
      "test_r2": 0.7105662388230767,
      "best_params": {
        "learning_rate": 0.01,
        "max_depth": 5,
        "n_estimators": 500,
        "subsample": 0.8
      }
    },
    {
      "config": "90n_30n",
      "model_type": "lstm",
      "success": true,
      "training_time": 6248.379997014999,
      "timestamp": "2025-10-04T04:50:34.948103",
      "test_rmse": 0.5176831963788668,
      "test_r2": 0.17881161500347875,
      "best_params": {
        "batch_size": 32,
        "dropout": 0.2,
        "n_layers": 2,
        "units": 64
      }
    }
  ],
  "errors": []
}